exespy/__init__.py
exespy/exespy.py
exespy/helpers.py
exespy/license_dialog.py
exespy/pe_file.py
exespy/state.py
exespy/tab_view.py
exespy/third_party_licenses.txt
exespy/img/icon.ico
exespy/img/icon.png
exespy/img/splash.png
exespy/img/wordmark.png
exespy/views/disassembly.py
exespy/views/entropy.py
exespy/views/exports.py
exespy/views/general.py
exespy/views/hashes.py
exespy/views/headers.py
exespy/views/hexview.py
exespy/views/imports.py
exespy/views/libraries.py
exespy/views/manifest.py
exespy/views/packers.py
exespy/views/resources.py
exespy/views/sections.py
exespy/views/strings.py
exespy/views/view.py
exespy/views/virustotal.py
exespy/views/components/table.py
exespy/views/components/textedit.py
exespy/yara/CREDITS.txt
exespy/yara/godaddy.yara
exespy/yara/packer.yara
exespy/yara/peid.yara
exespy-1.0.1.dist-info/LICENSE
exespy-1.0.1.dist-info/METADATA
exespy-1.0.1.dist-info/WHEEL
exespy-1.0.1.dist-info/entry_points.txt
exespy-1.0.1.dist-info/top_level.txt
exespy-1.0.1.dist-info/RECORD
