Metadata-Version: 2.1
Name: exespy
Version: 1.0.1
Summary: Cross-platform PE viewer
Home-page: https://github.com/andyjsmith/Exe-Spy
Author: Andy Smith
Keywords: pe,forensics,windows forensics,forensics tools
Classifier: Programming Language :: Python :: 3
Classifier: Programming Language :: Python :: 3.8
Classifier: Programming Language :: Python :: 3.9
Classifier: Programming Language :: Python :: 3.10
Classifier: Programming Language :: Python :: 3.11
Classifier: Programming Language :: Python :: 3.12
Classifier: License :: OSI Approved :: GNU General Public License v3 (GPLv3)
Classifier: Operating System :: OS Independent
Classifier: Environment :: Win32 (MS Windows)
Classifier: Environment :: X11 Applications
Classifier: Environment :: X11 Applications :: Qt
Classifier: Environment :: MacOS X
Requires-Python: >=3.8
License-File: LICENSE
Requires-Dist: PySide6
Requires-Dist: pefile
Requires-Dist: lief
Requires-Dist: icoextract
Requires-Dist: yara-python
Requires-Dist: iced-x86
Requires-Dist: vt-py
Requires-Dist: matplotlib
Requires-Dist: python-magic ; platform_system != "Windows" and platform_system != "Darwin"
Requires-Dist: python-magic-bin ; platform_system == "Windows" or platform_system == "Darwin"
